{
    "vendor":    "Sonore",
    "model":     "ultraRendu",
    "vendor_model":     "ultraRendu",
    "serial":    "01531B",
    "version":   "2.8",
    "unique_id": "2db26fbd-00de-43a3-8b8a-3f384fcc9d13",
    "config_url": "http://__SELF__/",
    "output":   {
        "type":            "alsa",
        "device":          "hw:0,0",
        "signal_path":     [ { "quality": "lossless", "type": "output", "method": "usb" } ],
        "dsd_mode":        "dop",
        "buffer_duration": 0.05
    },
    "watch":    {
        "type":            "alsa",
        "device":          "hw:0,0",
        "lost_action":     "exit"
    },
    "volume":   {
        "type":            "null",
        "optional":        true
    }
}
